cli_tools/__init__.py
cli_tools/main_cli.py
cli_tools/organize_cli.py
cli_tools/requirements_cli.py
cli_tools/utility_cli.py
config/__init__.py
config/manager.py
config/models.py
organize/__init__.py
organize/backup_manager.py
organize/directory_creator.py
organize/exclusion_utils.py
organize/file_organizer.py
organize/models.py
organize/name_only_reorganizer.py
organize/simple_classifier.py
organize/structure_validator.py
organize/template_parser.py
requirements/__init__.py
requirements/git_integration.py
requirements/kiro_parser.py
requirements/living_document.py
requirements/models.py
requirements/requirements_aggregator.py
requirements/tracker.py
gjalla-0.1.1.dist-info/METADATA
gjalla-0.1.1.dist-info/WHEEL
gjalla-0.1.1.dist-info/entry_points.txt
gjalla-0.1.1.dist-info/top_level.txt
gjalla-0.1.1.dist-info/RECORD
