Metadata-Version: 2.4
Name: gjalla
Version: 0.1.1
Summary: CLI tool for organizing, aggregating, and standardizing requirements and architecture information from markdowns written by agentic coding tools.
Home-page: https://github.com/elliemdaw/gjalla-cli
Author: Ellie
Author-email: ellie@gjalla.io
Project-URL: Bug Reports, https://github.com/elliemdaw/gjalla-cli/issues
Project-URL: Source, https://github.com/elliemdaw/gjalla-cli
Keywords: documentation markdown validation standardization cli ai
Classifier: Development Status :: 3 - Alpha
Classifier: Intended Audience :: Developers
Classifier: License :: OSI Approved :: MIT License
Classifier: Operating System :: OS Independent
Classifier: Programming Language :: Python :: 3
Classifier: Programming Language :: Python :: 3.8
Classifier: Programming Language :: Python :: 3.9
Classifier: Programming Language :: Python :: 3.10
Classifier: Programming Language :: Python :: 3.11
Classifier: Topic :: Documentation
Classifier: Topic :: Software Development :: Documentation
Classifier: Topic :: Text Processing :: Markup
Requires-Python: >=3.8
Requires-Dist: cryptography>=3.4.8
Requires-Dist: requests>=2.25.1
Requires-Dist: click>=8.0.0
Requires-Dist: pydantic>=1.8.0
Requires-Dist: rich>=10.0.0
Requires-Dist: pathlib2>=2.3.6; python_version < "3.4"
Requires-Dist: spacy>=3.4.0
Provides-Extra: dev
Requires-Dist: pytest>=6.0.0; extra == "dev"
Requires-Dist: pytest-cov>=2.10.0; extra == "dev"
Requires-Dist: black>=21.0.0; extra == "dev"
Requires-Dist: flake8>=3.8.0; extra == "dev"
Requires-Dist: mypy>=0.812; extra == "dev"
Dynamic: author
Dynamic: author-email
Dynamic: classifier
Dynamic: description
Dynamic: description-content-type
Dynamic: home-page
Dynamic: keywords
Dynamic: project-url
Dynamic: provides-extra
Dynamic: requires-dist
Dynamic: requires-python
Dynamic: summary
